tree/__init__.py
tree/cli.py
tree/tree_util.py
tree_peb-0.1.0.dist-info/LICENSE
tree_peb-0.1.0.dist-info/METADATA
tree_peb-0.1.0.dist-info/WHEEL
tree_peb-0.1.0.dist-info/top_level.txt
tree_peb-0.1.0.dist-info/RECORD
