Metadata-Version: 2.1
Name: tree-peb
Version: 0.1.0
Summary: List contents of directories in tree-like format.
Author-email: peb <singh.harsh9097@gmail.com>
Project-URL: Homepage, https://github.com/peb-peb/tree
Classifier: Programming Language :: Python :: 3
Classifier: License :: OSI Approved :: MIT License
Classifier: Operating System :: OS Independent
Requires-Python: >=3.7
License-File: LICENSE
